LICENSE
README.md
agrigee_lite/__init__.py
agrigee_lite/aria2.conf
agrigee_lite/downloader.py
agrigee_lite/ee_utils.py
agrigee_lite/misc.py
agrigee_lite/task_manager.py
agrigee_lite/tgui_task_manager.py
agrigee_lite/vegetation_indices.py
agrigee_lite/get/__init__.py
agrigee_lite/get/image.py
agrigee_lite/get/sits.py
agrigee_lite/sat/__init__.py
agrigee_lite/sat/abstract_satellite.py
agrigee_lite/sat/dem.py
agrigee_lite/sat/embeddings.py
agrigee_lite/sat/hls.py
agrigee_lite/sat/landsat.py
agrigee_lite/sat/mapbiomas.py
agrigee_lite/sat/modis.py
agrigee_lite/sat/palsar.py
agrigee_lite/sat/sentinel1.py
agrigee_lite/sat/sentinel2.py
agrigee_lite/sat/soil.py
agrigee_lite/sat/unified_satellite.py
agrigee_lite/vis/__init__.py
agrigee_lite/vis/images.py
agrigee_lite/vis/sits.py
agrigee_lite-2.0.12.dist-info/METADATA
agrigee_lite-2.0.12.dist-info/WHEEL
agrigee_lite-2.0.12.dist-info/entry_points.txt
agrigee_lite-2.0.12.dist-info/licenses/LICENSE
agrigee_lite-2.0.12.dist-info/RECORD
