Metadata-Version: 2.4
Name: agrigee_lite
Version: 2.0.12
Summary: Because using satellite data should not be rocket science.
Project-URL: Homepage, https://mateuspinto.github.io/agrigee_lite/
Project-URL: Repository, https://github.com/mateuspinto/agrigee_lite
Project-URL: Documentation, https://mateuspinto.github.io/agrigee_lite/
Author-email: Mateus Pinto da Silva <mateus.p.silva@ufv.br>
License-File: LICENSE
Keywords: python
Classifier: Intended Audience :: Developers
Classifier: Programming Language :: Python
Classifier: Programming Language :: Python :: 3
Classifier: Programming Language :: Python :: 3.10
Classifier: Programming Language :: Python :: 3.11
Classifier: Programming Language :: Python :: 3.12
Classifier: Programming Language :: Python :: 3.13
Classifier: Topic :: Software Development :: Libraries :: Python Modules
Requires-Python: <4.0,>=3.10
Requires-Dist: aria2p>=0.12.1
Requires-Dist: earthengine-api>=1.5.7
Requires-Dist: ee-s1-ard>=1.0.5
Requires-Dist: geopandas>=1.0.1
Requires-Dist: pandera>=0.26.1
Requires-Dist: topojson>=1.9
Requires-Dist: tqdm>=4.67.1
Provides-Extra: all
Requires-Dist: matplotlib>=3.10.1; extra == 'all'
Requires-Dist: plotly>=6.2.0; extra == 'all'
Requires-Dist: pyarrow>=19.0.1; extra == 'all'
Requires-Dist: smart-open[gcs]>=7.1.0; extra == 'all'
Requires-Dist: textual-pandas>=0.2.3; extra == 'all'
Provides-Extra: tasks
Requires-Dist: pyarrow>=19.0.1; extra == 'tasks'
Requires-Dist: smart-open[gcs]>=7.1.0; extra == 'tasks'
Requires-Dist: textual-pandas>=0.2.3; extra == 'tasks'
Provides-Extra: visualization
Requires-Dist: matplotlib>=3.10.1; extra == 'visualization'
Requires-Dist: plotly>=6.2.0; extra == 'visualization'
